<?xml version="1.0" encoding="UTF-8" standalone="yes" ?>
<dataInfo xmlns="http://www.egi.com/info_n_mff" xmlns:xsi="http://www.w3.org/2001/XMLSchema-instance">
    <generalInformation>
        <fileDataType>
            <EEG>
                <EEGFile />
                <sensorLayoutName>HydroCel GSN 128 1.0</sensorLayoutName>
                <montageName>HydroCel GSN 128 1.0</montageName>
            </EEG>
        </fileDataType>
    </generalInformation>
    <hardwareFilterAdjusted shiftMicroseconds="66000">true</hardwareFilterAdjusted>
    <calibrations>
        <calibration>
            <beginTime>0</beginTime>
            <endTime>0</endTime>
            <type>GCAL</type>
            <channels>
                <ch n="1">0.9931390624999999</ch>
                <ch n="2">0.9930864257812499</ch>
                <ch n="693">0.99397158203125</ch>
                <ch n="4">0.9939775390625001</ch>
                <ch n="705">0.9926880859375001</ch>
                <ch n="">0.99285546875</ch>
                <ch n="7">0.9937982421875</ch>
                <ch n="728">0.99326875</ch>
                <ch n="9">0.99261708984375</ch>
                <ch n="10">0.9923388671875</ch>
                <ch n="11">0.9940271484375</ch>
                <ch n="12">0.99280830078125</ch>
                <ch n="13">0.9925450195312501</ch>
                <ch n="14">0.99219541015625</ch>
                <ch n="15">0.99345244140625</ch>
                <ch n="16">0.99332333984375</ch>
                <ch n="17">0.99304912109375</ch>
                <ch n="18">0.9926666992187499</ch>
                <ch n="19">0.99427109375</ch>
                <ch n="20">0.993808203125</ch>
                <ch n="21">0.9930189453125</ch>
                <ch n="22">0.99288916015625</ch>
                <ch n="23">0.9942139648437501</ch>
                <ch n="24">0.9937544921875001</ch>
                <ch n="25">0.9935329101562501</ch>
                <ch n="">0.9928276367187501</ch>
                <ch n="27">0.9944240234375</ch>
                <ch n="28">0.9942080078125</ch>
                <ch n="29">0.99345400390625</ch>
                <ch n="30">0.9930228515625001</ch>
                <ch n="31">0.99419560546875</ch>
                <ch n="32">0.99406201171875</ch>
                <ch n="33">0.9925712890625</ch>
                <ch n="34">0.992319921875</ch>
                <ch n="35">0.99387275390625</ch>
                <ch n="36">0.9929478515625</ch>
                <ch n="37">0.99278837890625</ch>
                <ch n="38">0.9924809570312501</ch>
                <ch n="39">0.9935101562500001</ch>
                <ch n="40">0.993634765625</ch>
                <ch n="41">0.992365234375</ch>
                <ch n="42">0.9921128906250001</ch>
                <ch n="43">0.99285146484375</ch>
                <ch n="44">0.9930615234375</ch>
                <ch n="9045">0.99175771484375</ch>
                <ch n="46">0.9915292968750001</ch>
                <ch n="47">0.9928564453125001</ch>
                <ch n="48">0.99251962890625</ch>
                <ch n="49">0.992894140625</ch>
                <ch n="50">0.9924670898437501</ch>
                <ch n="51">0.9932632812500001</ch>
                <ch n="52">0.992948828125</ch>
                <ch n="53">0.992290234375</ch>
                <ch n="54">0.9922847656250001</ch>
                <ch n="55">0.99314794921875</ch>
                <ch n="56">0.99328505859375</ch>
                <ch n="57">0.99325380859375</ch>
                <ch n="58">0.9930249023437501</ch>
                <ch n="59">0.9937450195312501</ch>
                <ch n="60">0.9937335937500001</ch>
                <ch n="61">0.99273623046875</ch>
                <ch n="62">0.99325927734375</ch>
                <ch n="63">0.9925763671875</ch>
                <ch n="64">0.9933392578125001</ch>
                <ch n="65">0.9926880859375001</ch>
                <ch n="66">0.992398046875</ch>
                <ch n="67">0.993828515625</ch>
                <ch n="10368">0.99388017578125</ch>
                <ch n="69">0.9926830078125</ch>
                <ch n="70">0.9923552734375</ch>
                <ch n="71">0.9931837890625</ch>
                <ch n="72">0.993771875</ch>
                <ch n="73">0.9935826171875001</ch>
                <ch n="74">0.993458984375</ch>
                <ch n="75">0.9947330078125</ch>
                <ch n="76">0.9945263671875</ch>
                <ch n="77">0.9936109375</ch>
                <ch n="78">0.9931525390625001</ch>
                <ch n="79">0.99433662109375</ch>
                <ch n="80">0.9941711914062501</ch>
                <ch n="81">0.9936208984375</ch>
                <ch n="82">0.99376884765625</ch>
                <ch n="83">0.9942685546875</ch>
                <ch n="84">0.99332734375</ch>
                <ch n="85">0.9933560546875001</ch>
                <ch n="86">0.99325380859375</ch>
                <ch n="87">0.994143359375</ch>
                <ch n="88">0.99380263671875</ch>
                <ch n="89">0.9926349609375001</ch>
                <ch n="90">0.99265673828125</ch>
                <ch n="91">0.99382158203125</ch>
                <ch n="92">0.9934033203125</ch>
                <ch n="11793">0.9929935546874999</ch>
                <ch n="94">0.99263583984375</ch>
                <ch n="95">0.9936128906250001</ch>
                <ch n="96">0.9931802734375</ch>
                <ch n="97">0.99337001953125</ch>
                <ch n="98">0.9932478515625001</ch>
                <ch n="99">0.99386025390625</ch>
                <ch n="100">0.9936193359375</ch>
                <ch n="101">0.99349326171875</ch>
                <ch n="102">0.99342021484375</ch>
                <ch n="122103">0.9933204101562502</ch>
                <ch n="104">0.9934197265625</ch>
                <ch n="105">0.9934892578125001</ch>
                <ch n="106">0.9929309570312501</ch>
                <ch n="124107">0.9933075195312501</ch>
                <ch n="108">0.99328603515625</ch>
                <ch n="109">0.9926339843750001</ch>
                <ch n="110">0.9929478515625</ch>
                <ch n="111">0.9933958984375</ch>
                <ch n="112">0.99283798828125</ch>
                <ch n="113">0.99366953125</ch>
                <ch n="114">0.99321259765625</ch>
                <ch n="115">0.99390849609375</ch>
                <ch n="116">0.99427802734375</ch>
                <ch n="117">0.9933884765625</ch>
                <ch n="129118">0.9926939453125</ch>
                <ch n="119">0.994071875</ch>
                <ch n="120">0.99326669921875</ch>
                <ch n="121">0.9941603515625</ch>
                <ch n="122">0.9938260742187501</ch>
                <ch n="123">0.9936809570312501</ch>
                <ch n="124">0.99387265625</ch>
                <ch n="125">0.99342216796875</ch>
                <ch n="126">0.9936830078125</ch>
                <ch n="127">0.99360888671875</ch>
                <ch n="128">0.993819140625</ch>
                <ch n="129">0.9932883338928226</ch>
            </channels>
        </calibration>
        <calibration>
            <beginTime>0</beginTime>
            <endTime>0</endTime>
            <type>ICAL</type>
            <channels>
                <ch n="1">117.1948149987454</ch>
                <ch n="2">42.01993951628224</ch>
                <ch n="3">21.56342901355818</ch>
                <ch n="4">70.56284613643017</ch>
                <ch n="5">41.67097398321338</ch>
                <ch n="6">36.79798741021036</ch>
                <ch n="87">50.09645661062855</ch>
                <ch n="8">7308.828061687536</ch>
                <ch n="9">90.27320423430835</ch>
                <ch n="10">72.58968774317096</ch>
                <ch n="10">22.7328196768074</ch>
                <ch n="12">16.02280206066954</ch>
                <ch n="13">35.39191775462496</ch>
                <ch n="14">89.89934538476484</ch>
                <ch n="15">19.29719385380699</ch>
                <ch n="16">18.40686545620192</ch>
                <ch n="17">49.45740757253569</ch>
                <ch n="18">38.26208506056673</ch>
                <ch n="19">65.32830969817412</ch>
                <ch n="20">40.42178153321176</ch>
                <ch n="21">74.41925920007719</ch>
                <ch n="22">72.37551833523291</ch>
                <ch n="23">85.88115584783439</ch>
                <ch n="24">99.15840613747935</ch>
                <ch n="25">52.2300866995757</ch>
                <ch n="26">32.47328958880058</ch>
                <ch n="27">88.50290561940297</ch>
                <ch n="28">40.42282217998866</ch>
                <ch n="29">80.09284743762083</ch>
                <ch n="30">17.71653501450788</ch>
                <ch n="31">37.58091308638697</ch>
                <ch n="32">45.38344394788892</ch>
                <ch n="33">16.49857271375373</ch>
                <ch n="34">60.53916023340595</ch>
                <ch n="35">34.42352478703859</ch>
                <ch n="36">59.26243388932777</ch>
                <ch n="37">39.72352802750544</ch>
                <ch n="38">67.54564795878747</ch>
                <ch n="39">33.9599623980738</ch>
                <ch n="2340">48.64871199848689</ch>
                <ch n="41">74.34947502433113</ch>
                <ch n="2442">84.88486429529534</ch>
                <ch n="43">47.26721617507783</ch>
                <ch n="2544">70.06575561601881</ch>
                <ch n="45">27.03754503854201</ch>
                <ch n="46">40.10095372505699</ch>
                <ch n="47">84.77113483700568</ch>
                <ch n="48">7504.528595676877</ch>
                <ch n="49">322.2231979733067</ch>
                <ch n="50">98.06134672865919</ch>
                <ch n="51">47.1762676587251</ch>
                <ch n="52">88.45662735881751</ch>
                <ch n="53">36.95307133524499</ch>
                <ch n="54">50.96298012224007</ch>
                <ch n="55">30.62192081138926</ch>
                <ch n="56">88.52708291519497</ch>
                <ch n="57">190.0386574366052</ch>
                <ch n="58">59.73597295038086</ch>
                <ch n="3259">53.12346088014054</ch>
                <ch n="60">96.14453319748006</ch>
                <ch n="61">59.29762214223912</ch>
                <ch n="3462">47.46316570228376</ch>
                <ch n="">467.5539121982759</ch>
                <ch n="3564">71.35186042986687</ch>
                <ch n="65">35.88370778093776</ch>
                <ch n="3666">70.37157429237276</ch>
                <ch n="67">48.95899457501162</ch>
                <ch n="3768">88.21861429140893</ch>
                <ch n="69">69.50072959492076</ch>
                <ch n="3870">44.85719870983183</ch>
                <ch n="71">23.61721739511104</ch>
                <ch n="72">72.6224106443475</ch>
                <ch n="73">355.9963725619222</ch>
                <ch n="74">44.42434008450402</ch>
                <ch n="75">57.37756278151199</ch>
                <ch n="76">31.26587715150421</ch>
                <ch n="4177">40.20499393297779</ch>
                <ch n="78">45.1762620961302</ch>
                <ch n="4279">30.2087478172223</ch>
                <ch n="80">33.52854083320325</ch>
                <ch n="4381">415.3313718471205</ch>
                <ch n="82">50.49881369221014</ch>
                <ch n="83">145.8941820071348</ch>
                <ch n="84">28.44674483232152</ch>
                <ch n="85">79.28324379287902</ch>
                <ch n="4586">59.57579515127416</ch>
                <ch n="87">40.09311851497921</ch>
                <ch n="88">60.33035159379682</ch>
                <ch n="89">88.22862541053019</ch>
                <ch n="90">24.05362874556964</ch>
                <ch n="91">40.64279516879773</ch>
                <ch n="92">74.68206365001208</ch>
                <ch n="93">43.90427656028836</ch>
                <ch n="94">7868.863492953226</ch>
                <ch n="95">40.71828947767499</ch>
                <ch n="96">42.56516648147223</ch>
                <ch n="97">1358.309553581015</ch>
                <ch n="5098">98.61989218130728</ch>
                <ch n="99">8535.108286853219</ch>
                <ch n="100">10000</ch>
                <ch n="101">5016.189207831774</ch>
                <ch n="102">54.56249818500173</ch>
                <ch n="103">42.84018077664147</ch>
                <ch n="104">47.52020687182332</ch>
                <ch n="105">44.39242340739628</ch>
                <ch n="106">76.96938677321343</ch>
                <ch n="547">7562.268795422127</ch>
                <ch n="108">68.34057803264068</ch>
                <ch n="109">38.0552729014671</ch>
                <ch n="110">37.21524324281035</ch>
                <ch n="111">48.61145023282917</ch>
                <ch n="112">81.08608892932166</ch>
                <ch n="113">8849.00657332339</ch>
                <ch n="57114">4593.202152758865</ch>
                <ch n="115">94.3889566243395</ch>
                <ch n="116">43.91018053089002</ch>
                <ch n="117">36.05157447779333</ch>
                <ch n="118">47.27816082833969</ch>
                <ch n="119">7695.488717250949</ch>
                <ch n="120">7617.557113723471</ch>
                <ch n="121">7672.442774071086</ch>
                <ch n="61122">46.86689422444045</ch>
                <ch n="123">16.18138938303824</ch>
                <ch n="124">42.02418482961747</ch>
                <ch n="125">8254.890887086127</ch>
                <ch n="126">6654.715577585812</ch>
                <ch n="127">4705.187103707452</ch>
                <ch n="128">63.1537284537871</ch>
                <ch n="129">58.5328216094949</ch>
            </channels>
        </calibration>
    </calibrations>
</dataInfo>
